presenterm_export/__init__.py
presenterm_export/__main__.py
presenterm_export/capture.py
presenterm_export/cli.py
presenterm_export/html.py
presenterm_export/image.py
presenterm_export/pdf.py
presenterm_export-0.2.7.dist-info/LICENSE.txt
presenterm_export-0.2.7.dist-info/METADATA
presenterm_export-0.2.7.dist-info/WHEEL
presenterm_export-0.2.7.dist-info/entry_points.txt
presenterm_export-0.2.7.dist-info/top_level.txt
presenterm_export-0.2.7.dist-info/RECORD
