Metadata-Version: 2.2
Name: presenterm-export
Version: 0.2.7
Summary: Presenterm's presentation exporter
Author-email: Matias Fontanini <matias.fontanini@gmail.com>
Maintainer-email: Matias Fontanini <matias.fontanini@gmail.com>
License: BSD 2-Clause License
Project-URL: Homepage, https://github.com/mfontanini/presenterm-export
Project-URL: Bug Reports, https://github.com/mfontanini/presenterm-export
Project-URL: Source, https://github.com/mfontanini/presenterm-export
Keywords: presenterm,terminal,slideshow
Requires-Python: >=3.9
License-File: LICENSE.txt
Requires-Dist: ansi2html==1.8.0
Requires-Dist: libtmux==0.23.2
Requires-Dist: weasyprint==62.3.0
Requires-Dist: dataclass-wizard==0.35.0
